[{"model": "groups.consumergroup", "pk": 1, "fields": {"nickname": "Barton, Mills and Joseph", "phone_number": "001-734-769-0041x517", "postal_code": "11343", "street_name": "Cooley Cliffs", "house_number": "621", "neighborhood": "East Heidi", "reference_location": "071 Mendez Crossroad Apt. 826\nEast Laura, PA 99789", "logo": "", "description": "Parent myself far. Have generation fish include bag.\nGreen be heavy pick church federal season. Hope choose present follow. Product wide great interesting reality investment others.", "created_at": "2024-03-17T23:29:55.068Z", "updated_at": "2024-03-17T23:29:55.068Z"}}, {"model": "groups.consumergroup", "pk": 2, "fields": {"nickname": "Grimes, Simmons and Davis", "phone_number": "+1-637-778-0856", "postal_code": "61548", "street_name": "Park Lane", "house_number": "136", "neighborhood": "New Amandaville", "reference_location": "66431 Jones Drive\nCoxview, WA 12822", "logo": "", "description": "Smile majority enter according. Around catch enjoy. Scientist car individual partner.\nForeign those past blue drive black but. Management game hotel music.", "created_at": "2024-03-17T23:29:55.093Z", "updated_at": "2024-03-17T23:29:55.094Z"}}, {"model": "groups.consumergroup", "pk": 3, "fields": {"nickname": "Johnson-Navarro", "phone_number": "280.684.0892x2212", "postal_code": "17534", "street_name": "Ramirez Ville", "house_number": "691", "neighborhood": "Parkerberg", "reference_location": "3172 Melissa Lock Suite 350\nWest Thomas, ID 24021", "logo": "", "description": "Manager son left around significant real. Prove teacher under citizen.\nWide bed avoid five sense should population. Example PM risk field natural pass low. Whose kind compare deep member drop.", "created_at": "2024-03-17T23:29:55.118Z", "updated_at": "2024-03-17T23:29:55.118Z"}}, {"model": "groups.consumergroup", "pk": 4, "fields": {"nickname": "Krause Ltd", "phone_number": "(253)590-0364x23014", "postal_code": "85999", "street_name": "Marc Way", "house_number": "17531", "neighborhood": "Port Paul", "reference_location": "7906 Patricia Mission Apt. 944\nHuertahaven, SD 35700", "logo": "", "description": "Sort let until significant consider specific contain matter. Dream east stuff alone base blood.", "created_at": "2024-03-17T23:29:55.140Z", "updated_at": "2024-03-17T23:29:55.140Z"}}, {"model": "groups.consumergroup", "pk": 5, "fields": {"nickname": "Salinas, Wright and Strong", "phone_number": "001-367-624-4760x361", "postal_code": "47965", "street_name": "Jane Street", "house_number": "02824", "neighborhood": "Lake Gina", "reference_location": "557 Scott Skyway\nWashingtonburgh, GA 64430", "logo": "", "description": "Person part listen themselves hour individual become. No attack box. Charge light present member wonder.", "created_at": "2024-03-17T23:29:55.166Z", "updated_at": "2024-03-17T23:29:55.166Z"}}, {"model": "groups.consumergroup", "pk": 6, "fields": {"nickname": "Davis-Allen", "phone_number": "515.427.3046", "postal_code": "79103", "street_name": "Matthew Meadows", "house_number": "9499", "neighborhood": "Keithfurt", "reference_location": "PSC 9057, Box 6824\nAPO AA 98917", "logo": "", "description": "Perform leader skin up remember be part. Move water yard all play in court. Attention series commercial sit dark can doctor indicate.", "created_at": "2024-03-17T23:29:55.190Z", "updated_at": "2024-03-17T23:29:55.190Z"}}, {"model": "groups.consumergroup", "pk": 7, "fields": {"nickname": "Carrillo, Armstrong and Gross", "phone_number": "001-385-847-2936x943", "postal_code": "70951", "street_name": "Fry Flat", "house_number": "7967", "neighborhood": "Stevenhaven", "reference_location": "00962 Mann Path Apt. 790\nFosterview, NE 21668", "logo": "", "description": "Chair energy may finally language. First site where glass unit only something ever.\nPoint style good share. Finally over develop three level fast.", "created_at": "2024-03-17T23:29:55.209Z", "updated_at": "2024-03-17T23:29:55.210Z"}}, {"model": "groups.consumergroup", "pk": 8, "fields": {"nickname": "Wang and Sons", "phone_number": "7372430319", "postal_code": "35689", "street_name": "Chad Estates", "house_number": "2404", "neighborhood": "New Michael", "reference_location": "USNS Ballard\nFPO AP 67667", "logo": "", "description": "Style certainly dog stuff energy quite. Own this hope threat serious campaign.\nOf project learn through society. Support cover hit Congress owner process majority spend.", "created_at": "2024-03-17T23:29:55.231Z", "updated_at": "2024-03-17T23:29:55.231Z"}}, {"model": "groups.consumergroup", "pk": 9, "fields": {"nickname": "Ramsey Group", "phone_number": "894-805-9058x9711", "postal_code": "03671", "street_name": "Alexander Freeway", "house_number": "354", "neighborhood": "South Louishaven", "reference_location": "72422 Lewis Ford\nCookfort, MI 12706", "logo": "", "description": "Such prepare stuff. Operation doctor material thing. Without movie explain work whose back.\nEffort general personal financial. Product play I director fine want customer.", "created_at": "2024-03-17T23:29:55.251Z", "updated_at": "2024-03-17T23:29:55.251Z"}}, {"model": "groups.consumergroup", "pk": 10, "fields": {"nickname": "West LLC", "phone_number": "+1-384-238-4725", "postal_code": "79810", "street_name": "Rogers Stream", "house_number": "69265", "neighborhood": "Port Kimberlyberg", "reference_location": "2006 Anderson Hollow Apt. 699\nAlyssaview, KY 15271", "logo": "", "description": "Especially store issue such. Position leg bag ready. Option shake laugh remain.\nGlass perform president though. Him until vote various memory green.\nSon bit seven.", "created_at": "2024-03-17T23:29:55.273Z", "updated_at": "2024-03-17T23:29:55.273Z"}}]